sphinx_genai_huggingface/__init__.py
sphinx_genai_huggingface/static/searchtools.js
sphinx_genai_huggingface/static/searchtools2.js
sphinx_genai_huggingface/static/sphinx-embeddings.js
sphinx_genai_huggingface-0.0.6.dist-info/METADATA
sphinx_genai_huggingface-0.0.6.dist-info/WHEEL
sphinx_genai_huggingface-0.0.6.dist-info/RECORD
